Metadata-Version: 1.0
Name: lazysquirrel
Version: 0.2.1
Summary: Initialize your programs & servers in one click
Home-page: https://github.com/omarking05/linux-init-script
Author: Omar Ahmed
Author-email: omar.ahmed.oaaem@gmail.com
License: MIT
Platform: UNKNOWN
